intake_geopandas/__init__.py
intake_geopandas/_version.py
intake_geopandas/geopandas.py
intake_geopandas/regionmask.py
tests/__init__.py
tests/test_file_source.py
tests/test_regionmask.py
tests/test_remote_cache.py
tests/test_sql_source.py
intake_geopandas-0.4.0.dist-info/LICENSE
intake_geopandas-0.4.0.dist-info/METADATA
intake_geopandas-0.4.0.dist-info/WHEEL
intake_geopandas-0.4.0.dist-info/entry_points.txt
intake_geopandas-0.4.0.dist-info/top_level.txt
intake_geopandas-0.4.0.dist-info/RECORD
