Metadata-Version: 2.1
Name: intake-geopandas
Version: 0.4.0
Summary: Geopandas plugin for Intake
Home-page: https://github.com/intake/intake_geopandas
Maintainer: Ian Rose
Maintainer-email: ian.r.rose@gmail.com
License: BSD
Platform: UNKNOWN
Classifier: Programming Language :: Python :: 3
Classifier: Programming Language :: Python :: 3.6
Classifier: Programming Language :: Python :: 3.7
Classifier: Programming Language :: Python :: 3.8
Requires-Python: >=3.6
License-File: LICENSE
Requires-Dist: geopandas
Requires-Dist: intake
Provides-Extra: arrow
Requires-Dist: pyarrow ; extra == 'arrow'
Provides-Extra: regionmask
Requires-Dist: regionmask ; extra == 'regionmask'
